compactdata/__init__.py
compactdata/char_constants.py
compactdata/decoder.py
compactdata/encoder.py
compactdata/escapes.py
compactdata/exceptions.py
compactdata/grammar_rules.py
compactdata/token_definitions.py
compactdata/unescapes.py
compactdata-0.0.4.dist-info/LICENSE
compactdata-0.0.4.dist-info/WHEEL
compactdata-0.0.4.dist-info/METADATA
compactdata-0.0.4.dist-info/RECORD
